{
   "inbound":
   {
      "id":"00",
      "name":"Inbound:",
      "value":0,
      "color":"",
      "type":"GLOBAL",
      "position":"LEFT",
      "time":"15:26:06",
      "textColor":"",
      "tooltip":""
   },
   "weborderquarantine":{
      "id":"0000",
      "name":"Weborder & Quarantäne:",
      "value":0,
      "color":"",
      "type":"HEADER",
      "position":"LEFT",
      "time":"15:26:07",
      "textColor":"",
      "tooltip":""
   },
   "weborderconnector":{
      "id":"0010",
      "name":"Weborder (Connector)",
      "value":18,
      "color":"black",
      "type":"DATA",
      "position":"LEFT",
      "time":"15:26:07",
      "textColor":"",
      "tooltip":"Logik: Letzte Connector/Datum/Zeit aelter [SCHWELLENWERT] Minuten als aktuelle Datum/Zeit = Farbe Rot\n1. Schwellwert: 0\n2. Schwellwert: 25 (red)\nOperator: >\nEinheit: MINUTE"
   },
   "weborder":{
      "id":"0020",
      "name":"Weborder",
      "value":18,
      "color":"black",
      "type":"DATA",
      "position":"LEFT",
      "time":"15:26:08",
      "textColor":"",
      "tooltip":"Logik: Älteste Connector/Datum/Zeit aelter [SCHWELLENWERT] Minuten als aktuelle Datum/Zeit = Farbe Gelb\n1. Schwellwert: 10 (yellow)\n2. Schwellwert: 20 (red)\nOperator: >\nEinheit: MINUTE"
   },
   "quarantineoldertoday":{
      "id":"0030",
      "name":"Quarantäne älter heute",
      "value":0,
      "color":"black",
      "type":"DATA",
      "position":"LEFT",
      "time":"15:26:08",
      "textColor":"",
      "tooltip":"Logik: Auftrag vorhanden bei dem Auftragsdatum < 1  Tag als Arbeitsdatum ist = Anzeige Gelb\n1. Schwellwert: 0\n2. Schwellwert: 999 (yellow)\nOperator: >\nEinheit: DAY"
   },
   "quarantineamount":{
      "id":"0035",
      "name":"Quarantäne Menge",
      "value":3,
      "color":"",
      "type":"DATA",
      "position":"LEFT",
      "time":"15:26:09",
      "textColor":"",
      "tooltip":"Logik: Quarantäne Auftragsmenge <  [SCHWELLENWERT] = Anzeige Gelb\n1. Schwellwert: 0\n2. Schwellwert: 100 (red)\nOperator: >\nEinheit: Anzahl"
   }
}
